numbits.cpython-39-darwin.so
numbits-0.0.1.dist-info/LICENSE
numbits-0.0.1.dist-info/METADATA
numbits-0.0.1.dist-info/WHEEL
numbits-0.0.1.dist-info/top_level.txt
numbits-0.0.1.dist-info/RECORD
