Metadata-Version: 2.1
Name: numbits
Version: 0.0.1
Summary: Pack and unpack 1, 2 and 4 bit data to/from 8-bit numpy arrays.
Home-page: https://github.com/telegraphic/numbits
Author: Danny Price
Author-email: dancpr@berkeley.edu
License: UNKNOWN
Project-URL: Source, https://github.com/telegraphic/numbits
Project-URL: Bug Reports, https://github.com/telegraphic/numbits/issues
Platform: UNKNOWN
Classifier: License :: OSI Approved :: MIT License
Classifier: Programming Language :: Python :: 3.6
Classifier: Programming Language :: Python :: 3.7
Classifier: Programming Language :: Python :: 3.8
Classifier: Programming Language :: Python :: 3.9
Classifier: Topic :: Scientific/Engineering :: Astronomy
Requires-Python: >=3.5, <4
